redh/__init__.py
redh/redh.py
redh-1.0.0.dist-info/LICENSE
redh-1.0.0.dist-info/METADATA
redh-1.0.0.dist-info/WHEEL
redh-1.0.0.dist-info/dependency_links.txt
redh-1.0.0.dist-info/entry_points.txt
redh-1.0.0.dist-info/top_level.txt
redh-1.0.0.dist-info/RECORD
