Metadata-Version: 2.1
Name: redh
Version: 1.0.0
Summary: Redhand is a command line tool for managing files and directories.
Home-page: https://github.com/mimseyedi/redh
Author: mimseyedi
Author-email: mim.seyedi@gmail.com
License: MIT
Classifier: License :: OSI Approved :: MIT License
Classifier: Programming Language :: Python :: 3
Classifier: Programming Language :: Python :: 3.6
Classifier: Programming Language :: Python :: 3.8
Requires-Python: >=3.6
License-File: LICENSE
Requires-Dist: click
